README.md
setup.cfg
setup.py
src/pyenv_loader/__init__.py
src/pyenv_loader/configuration.py
src/pyenv_loader/environment.py
src/pyenv_loader/utils.py
src/pyenv_loader.egg-info/PKG-INFO
src/pyenv_loader.egg-info/SOURCES.txt
src/pyenv_loader.egg-info/dependency_links.txt
src/pyenv_loader.egg-info/requires.txt
src/pyenv_loader.egg-info/top_level.txt