Metadata-Version: 2.1
Name: pyenv-loader
Version: 0.5
Summary: A simple Package to load & parse configuration to diffrent datatypes
Home-page: https://github.com/rionzz-inc/pyenv-loader
Author: Prakash Leon Mishra
Author-email: dev.leonmishra@gmail.com
License: MIT
Project-URL: Bug Tracker, https://github.com/rionzz-inc/pyenv-loader/issues
Project-URL: repository, https://github.com/rionzz-inc/pyenv-loader
Keywords: Python env loader,django configuration loader,flask config loader
Platform: UNKNOWN
Classifier: Programming Language :: Python :: 3
Classifier: License :: OSI Approved :: MIT License
Classifier: Operating System :: OS Independent
Requires-Python: >=3.0
